.gitignore
.travis.yml
CHANGES.rst
Makefile
README.rst
requirements.txt
runtests.py
setup.py
docs/Makefile
docs/api.rst
docs/changelog.rst
docs/conf.py
docs/config.rst
docs/design.rst
docs/development.rst
docs/glossary.rst
docs/index.rst
docs/install.rst
docs/jobs.rst
docs/logging.rst
docs/make.bat
docs/_themes/qdo/layout.html
docs/_themes/qdo/theme.conf
docs/api/log.rst
docs/api/partition.rst
docs/api/worker.rst
etc/qdo-worker.conf
etc/queuey.ini
etc/supervisord.conf
qdo/__init__.py
qdo/config.py
qdo/log.py
qdo/partition.py
qdo/runner.py
qdo/testing.py
qdo/worker.py
qdo.egg-info/PKG-INFO
qdo.egg-info/SOURCES.txt
qdo.egg-info/dependency_links.txt
qdo.egg-info/entry_points.txt
qdo.egg-info/not-zip-safe
qdo.egg-info/requires.txt
qdo.egg-info/top_level.txt
qdo/tests/__init__.py
qdo/tests/base.py
qdo/tests/test_config.py
qdo/tests/test_partition.py
qdo/tests/test_runner.py
qdo/tests/test_worker.py
qdo/tests/data/test.conf
sw/virtualenv.py
var/README.txt
var/log/README.txt