Metadata-Version: 1.1
Name: qdo
Version: 0.1
Summary: Queuey worker library
Home-page: http://qdo.readthedocs.org/
Author: Mozilla Services
Author-email: services-dev@mozilla.org
License: MPLv2.0
Platform: UNKNOWN
Classifier: Development Status :: 4 - Beta
Classifier: Environment :: Web Environment
Classifier: Intended Audience :: Developers
Classifier: License :: OSI Approved :: Mozilla Public License 2.0 (MPL 2.0)
Classifier: Programming Language :: Python
Classifier: Programming Language :: Python :: 2.6
Classifier: Programming Language :: Python :: 2.7
